send_wechat.py
send_wechat-0.0.3.dist-info/METADATA
send_wechat-0.0.3.dist-info/RECORD
send_wechat-0.0.3.dist-info/WHEEL
send_wechat-0.0.3.dist-info/top_level.txt
