Metadata-Version: 2.1
Name: send-wechat
Version: 0.0.3
Summary: get the eye state from the landmarks of the face in the image
Home-page: http://www.zhaomingming.cn
Author: zhaomingming
Author-email: 13271929138@163.com
License: MIT
Platform: any
